{
  "properties": {
    "activities": [
      {
        "type": "Copy",
        "typeProperties": {
          "source": {
            "type": "DelimitedTextSource",
            "formatSettings": {
              "type": "DelimitedTextReadSettings"
            },
            "storeSettings": {
              "type": "LakehouseReadSettings",
              "recursive": false,
              "wildcardFolderPath": "raw",
              "wildcardFileName": "*.csv",
              "enablePartitionDiscovery": false
            },
            "datasetSettings": {
              "type": "DelimitedText",
              "typeProperties": {
                "location": {
                  "type": "LakehouseLocation"
                },
                "columnDelimiter": ",",
                "quoteChar": "\"",
                "escapeChar": "\\",
                "firstRowAsHeader": true
              },
              "schema": [],
              "linkedService": {
                "name": "hr_attrition_lakehouse",
                "properties": {
                  "type": "Lakehouse",
                  "typeProperties": {
                    "artifactId": "e7c3ce06-67e2-a15e-44a8-39c94f2e745f",
                    "workspaceId": "00000000-0000-0000-0000-000000000000",
                    "rootFolder": "Files"
                  },
                  "annotations": []
                }
              },
              "annotations": []
            }
          },
          "sink": {
            "type": "ParquetSink",
            "formatSettings": {
              "type": "ParquetWriteSettings",
              "enableVertiParquet": true
            },
            "storeSettings": {
              "type": "LakehouseWriteSettings"
            },
            "datasetSettings": {
              "type": "Parquet",
              "typeProperties": {
                "location": {
                  "type": "LakehouseLocation",
                  "folderPath": "bronze"
                },
                "compressionCodec": "snappy"
              },
              "schema": [],
              "linkedService": {
                "name": "hr_attrition_lakehouse",
                "properties": {
                  "type": "Lakehouse",
                  "typeProperties": {
                    "artifactId": "e7c3ce06-67e2-a15e-44a8-39c94f2e745f",
                    "workspaceId": "00000000-0000-0000-0000-000000000000",
                    "rootFolder": "Files"
                  },
                  "annotations": []
                }
              },
              "annotations": []
            }
          },
          "translator": {
            "type": "TabularTranslator",
            "typeConversion": true,
            "typeConversionSettings": {
              "allowDataTruncation": true,
              "treatBooleanAsNumber": false
            }
          },
          "enableStaging": false
        },
        "policy": {
          "timeout": "0.12:00:00",
          "retry": 0,
          "retryIntervalInSeconds": 30,
          "secureInput": false,
          "secureOutput": false
        },
        "name": "Copy CSV",
        "dependsOn": []
      },
      {
        "type": "Copy",
        "typeProperties": {
          "source": {
            "type": "ExcelSource",
            "storeSettings": {
              "type": "LakehouseReadSettings",
              "recursive": true,
              "enablePartitionDiscovery": false
            },
            "datasetSettings": {
              "type": "Excel",
              "typeProperties": {
                "location": {
                  "type": "LakehouseLocation",
                  "folderPath": "raw",
                  "fileName": "employee_salaries.xlsx"
                },
                "sheetName": "Sheet1"
              },
              "schema": [],
              "linkedService": {
                "name": "hr_attrition_lakehouse",
                "properties": {
                  "type": "Lakehouse",
                  "typeProperties": {
                    "artifactId": "e7c3ce06-67e2-a15e-44a8-39c94f2e745f",
                    "workspaceId": "00000000-0000-0000-0000-000000000000",
                    "rootFolder": "Files"
                  },
                  "annotations": []
                }
              },
              "annotations": []
            }
          },
          "sink": {
            "type": "ParquetSink",
            "formatSettings": {
              "type": "ParquetWriteSettings",
              "enableVertiParquet": true
            },
            "storeSettings": {
              "type": "LakehouseWriteSettings"
            },
            "datasetSettings": {
              "type": "Parquet",
              "typeProperties": {
                "location": {
                  "type": "LakehouseLocation",
                  "folderPath": "bronze"
                },
                "compressionCodec": "snappy"
              },
              "schema": [],
              "linkedService": {
                "name": "hr_attrition_lakehouse",
                "properties": {
                  "type": "Lakehouse",
                  "typeProperties": {
                    "artifactId": "e7c3ce06-67e2-a15e-44a8-39c94f2e745f",
                    "workspaceId": "00000000-0000-0000-0000-000000000000",
                    "rootFolder": "Files"
                  },
                  "annotations": []
                }
              },
              "annotations": []
            }
          },
          "translator": {
            "type": "TabularTranslator",
            "typeConversion": true,
            "typeConversionSettings": {
              "allowDataTruncation": true,
              "treatBooleanAsNumber": false
            }
          },
          "enableStaging": false
        },
        "policy": {
          "timeout": "0.12:00:00",
          "retry": 0,
          "retryIntervalInSeconds": 30,
          "secureInput": false,
          "secureOutput": false
        },
        "name": "Copy_Excel",
        "dependsOn": [
          {
            "activity": "Copy CSV",
            "dependencyConditions": [
              "Succeeded"
            ]
          }
        ]
      },
      {
        "type": "RefreshDataflow",
        "typeProperties": {
          "dataflowId": "0ef14ffa-d7ed-b985-41ca-941471b88b85",
          "workspaceId": "00000000-0000-0000-0000-000000000000",
          "notifyOption": "NoNotification",
          "dataflowType": "DataflowFabric"
        },
        "policy": {
          "timeout": "0.12:00:00",
          "retry": 0,
          "retryIntervalInSeconds": 30,
          "secureInput": false,
          "secureOutput": false
        },
        "name": "DF_Clean",
        "dependsOn": [
          {
            "activity": "Copy_Excel",
            "dependencyConditions": [
              "Succeeded"
            ]
          }
        ]
      },
      {
        "type": "RefreshDataflow",
        "typeProperties": {
          "dataflowId": "99c37145-b519-8ec9-4623-40055d0ba452",
          "workspaceId": "00000000-0000-0000-0000-000000000000",
          "notifyOption": "NoNotification",
          "dataflowType": "DataflowFabric"
        },
        "policy": {
          "timeout": "0.12:00:00",
          "retry": 0,
          "retryIntervalInSeconds": 30,
          "secureInput": false,
          "secureOutput": false
        },
        "name": "DF_Merge",
        "dependsOn": [
          {
            "activity": "DF_Clean",
            "dependencyConditions": [
              "Succeeded"
            ]
          }
        ]
      }
    ]
  }
}